mcp_server_jupyter/__init__.py
mcp_server_jupyter/notebook_cell.py
mcp_server_jupyter/notebook_manager.py
mcp_server_jupyter/server.py
mcp_server_jupyter-0.1.9.dist-info/METADATA
mcp_server_jupyter-0.1.9.dist-info/WHEEL
mcp_server_jupyter-0.1.9.dist-info/entry_points.txt
mcp_server_jupyter-0.1.9.dist-info/licenses/LICENSE
mcp_server_jupyter-0.1.9.dist-info/RECORD
