Metadata-Version: 2.4
Name: mcp-server-jupyter
Version: 0.1.9
Summary: MCP server for Jupyter notebooks
Project-URL: Repository, https://github.com/ihrpr/mcp-server-jupyter
Project-URL: Issues, https://github.com/ihrpr/mcp-server-jupyter/issues
License: MIT
License-File: LICENSE
Classifier: Development Status :: 4 - Beta
Classifier: Intended Audience :: Developers
Classifier: License :: OSI Approved :: MIT License
Classifier: Programming Language :: Python :: 3
Classifier: Programming Language :: Python :: 3.10
Classifier: Programming Language :: Python :: 3.11
Classifier: Programming Language :: Python :: 3.12
Classifier: Programming Language :: Python :: 3.13
Requires-Python: >=3.10
Requires-Dist: ipykernel>=6.29.5
Requires-Dist: mcp[cli]>=1.2.0
Requires-Dist: nbclient>=0.10.2
Requires-Dist: nbformat>=5.10.4
Requires-Dist: pillow>=11.0.0
Requires-Dist: starlette>=0.36.0
Requires-Dist: uvicorn>=0.27.0
